MANIFEST.in
setup.cfg
setup.py
lava_kernel_ci_views.egg-info/PKG-INFO
lava_kernel_ci_views.egg-info/SOURCES.txt
lava_kernel_ci_views.egg-info/dependency_links.txt
lava_kernel_ci_views.egg-info/entry_points.txt
lava_kernel_ci_views.egg-info/not-zip-safe
lava_kernel_ci_views.egg-info/requires.txt
lava_kernel_ci_views.egg-info/top_level.txt
lava_kernel_ci_views_app/__init__.py
lava_kernel_ci_views_app/admin.py
lava_kernel_ci_views_app/extension.py
lava_kernel_ci_views_app/helpers.py
lava_kernel_ci_views_app/models.py
lava_kernel_ci_views_app/tests.py
lava_kernel_ci_views_app/urls.py
lava_kernel_ci_views_app/views.py
lava_kernel_ci_views_app/migrations/0001_initial.py
lava_kernel_ci_views_app/migrations/__init__.py
lava_kernel_ci_views_app/static/lava_kernel_ci_views_app/css/nested-render.css
lava_kernel_ci_views_app/static/lava_kernel_ci_views_app/js/nested-render.js
lava_kernel_ci_views_app/templates/lava_kernel_ci_views_app/compile_only.html
lava_kernel_ci_views_app/templates/lava_kernel_ci_views_app/index.html
lava_kernel_ci_views_app/templates/lava_kernel_ci_views_app/per_board.html
lava_kernel_ci_views_app/templates/lava_kernel_ci_views_app/waterfall.html