Metadata-Version: 1.0
Name: lava-kernel-ci-views
Version: 0.4.1
Summary: LAVA Kernel CI Views Application
Home-page: UNKNOWN
Author: Michael Hudson-Doyle
Author-email: michael.hudson@linaro.org
License: AGPL
Platform: UNKNOWN
